etlup/__about__.py
etlup/__init__.py
etlup/base_model.py
etlup/custom_types.py
etlup/example_formatter.py
etlup/fake/__init__.py
etlup/fake/fake_test_component.py
etlup/fake/fake_test_module.py
etlup/gantry/PickAndPlace.py
etlup/gantry/SubassemblyAlignment.py
etlup/gantry/__init__.py
etlup/image_tests/ImageTest.py
etlup/image_tests/__init__.py
etlup/module/ModuleIV.py
etlup/module/__init__.py
etlup/plot_utils.py
etlup/sensor/ChargeCollection.py
etlup/sensor/CurrentStability.py
etlup/sensor/CurrentUniformity.py
etlup/sensor/GainCurve.py
etlup/sensor/GainLayerUniformity.py
etlup/sensor/InterpadResistance.py
etlup/sensor/InterpadWidth.py
etlup/sensor/MPVStability.py
etlup/sensor/SensorIV.py
etlup/sensor/TestArrayCV.py
etlup/sensor/TestArrayIV.py
etlup/sensor/TimeResolution.py
etlup/sensor/__init__.py
etlup/sequences.py
etlup/tamalero/Baseline.py
etlup/tamalero/Mux64Values.py
etlup/tamalero/Noisewidth.py
etlup/tamalero/ReadoutBoardCommunication.py
etlup/tamalero/__init__.py
etlup/templates/sensors_plot.html
etlup/templates/test_by_image.html
etlup/upload.py
etlup-4.1.5.dist-info/WHEEL
etlup-4.1.5.dist-info/METADATA
etlup-4.1.5.dist-info/RECORD
