Metadata-Version: 2.4
Name: etlup
Version: 4.1.5
Summary: Test definitions, plotting and documentation for the CMS MTD ETL project
Author: Hayden Swanson
Author-email: Hayden Swanson <hayden.swanson@cern.ch>
License-Expression: MIT AND (Apache-2.0 OR BSD-2-Clause)
Requires-Dist: requests==2.31.0
Requires-Dist: jinja2==3.1.2
Requires-Dist: pydantic==2.8.2
Requires-Dist: matplotlib~=3.7
Requires-Dist: numpy~=1.20
Requires-Dist: pytz==2022.7
Maintainer: Hayden Swanson, Naomi Gonzalez
Maintainer-email: Hayden Swanson <hayden.swanson@cern.ch>, Naomi Gonzalez <ngonzalz@bu.edu>
Requires-Python: >=3.8
